base_kravata/__init__.py
base_kravata/config.py
base_kravata/container.py
base_kravata/decorator.py
base_kravata/encrypter.py
base_kravata/exceptions.py
base_kravata/logger.py
base_kravata/model.py
base_kravata/repository.py
base_kravata/schema.py
base_kravata/template_repository.py
base_kravata/template_service.py
base_kravata/test.py
base_kravata/utils.py
base_kravata/integrations/__init__.py
base_kravata/integrations/access_api.py
base_kravata/integrations/base_integration.py
base_kravata/integrations/client_api.py
base_kravata/integrations/external_api.py
base_kravata/integrations/partner_api.py
base_kravata/integrations/models/__init__.py
base_kravata/integrations/models/client_schema.py
base_kravata/integrations/models/crypto_account_schema.py
base_kravata/integrations/models/user_schema.py
base_kravata/mocks/__init__.py
base_kravata/mocks/mock_service.py
base_kravata/mocks/mocks.py
base_kravata-1.0.0.dist-info/METADATA
base_kravata-1.0.0.dist-info/WHEEL
base_kravata-1.0.0.dist-info/licenses/LICENSE.txt
base_kravata-1.0.0.dist-info/RECORD
