Metadata-Version: 2.3
Name: base_kravata
Version: 1.0.0
Summary: Contiene toda la base necesaria con la que kravata opera su ORM o conexiones a microservicios
Author-email: Braiam Patino <braiam@kravata.co>, Leonardo Delgado <leonardo@kravata.co>
Maintainer-email: Braiam Patino <braiam@kravata.co>
License: The MIT License (MIT)
License-File: LICENSE.txt
Keywords: kravata,orm
Classifier: Development Status :: 4 - Beta
Classifier: Programming Language :: Python
Requires-Python: >=3.8
Requires-Dist: flask
